isic_metadata/__init__.py
isic_metadata/diagnosis_hierarchical.py
isic_metadata/fields.py
isic_metadata/metadata.py
isic_metadata/py.typed
isic_metadata/utils.py
isic_metadata-4.11.0.dist-info/licenses/LICENSE
tests/__init__.py
tests/test_batch.py
tests/test_dependent_fields.py
tests/test_fields.py
tests/test_hierarchical_diagnosis.py
tests/test_utils.py
isic_metadata-4.11.0.dist-info/METADATA
isic_metadata-4.11.0.dist-info/WHEEL
isic_metadata-4.11.0.dist-info/top_level.txt
isic_metadata-4.11.0.dist-info/RECORD
